jsm_log_middleware/__init__.py
jsm_log_middleware/apps.py
jsm_log_middleware/middleware.py
jsm_log_middleware-0.2.1.dist-info/METADATA
jsm_log_middleware-0.2.1.dist-info/WHEEL
jsm_log_middleware-0.2.1.dist-info/top_level.txt
jsm_log_middleware-0.2.1.dist-info/RECORD
